PowerDB.py
powerdb-2.2.5.4.dist-info/METADATA
powerdb-2.2.5.4.dist-info/WHEEL
powerdb-2.2.5.4.dist-info/licenses/LICENSE
powerdb-2.2.5.4.dist-info/RECORD
