Metadata-Version: 2.4
Name: PowerDB
Version: 2.2.5.4
Summary: a DBM which is fast & easy to use for local small scale databases
Project-URL: Homepage, https://github.com/WeDu-official/PowerDB
Project-URL: Issues, https://github.com/WeDu-official/PowerDB/issues
Author-email: WeDu-official <fplu.the.founder@gmail.com>
License-File: LICENSE
Classifier: Development Status :: 6 - Mature
Classifier: Intended Audience :: Developers
Classifier: License :: Other/Proprietary License
Classifier: Natural Language :: English
Classifier: Operating System :: Microsoft :: Windows :: Windows 8.1
Classifier: Operating System :: Microsoft :: Windows :: Windows 10
Classifier: Operating System :: Microsoft :: Windows :: Windows 11
Classifier: Programming Language :: Python :: 3.8
Classifier: Programming Language :: Python :: 3.9
Classifier: Programming Language :: Python :: 3.10
Classifier: Programming Language :: Python :: 3.11
Classifier: Programming Language :: Python :: 3.12
Classifier: Programming Language :: Python :: 3.13
Classifier: Topic :: Database
Requires-Python: >=3.8
Requires-Dist: openpyxl>=3.1.5
